looker_loader/cli.py
looker_loader/enums.py
looker_loader/exceptions.py
looker_loader/utils.py
looker_loader/databases/bigquery/database.py
looker_loader/databases/bigquery/enums.py
looker_loader/generator/lookml.py
looker_loader/models/config.py
looker_loader/models/database.py
looker_loader/models/lex.py
looker_loader/models/looker.py
looker_loader/models/recipe.py
looker_loader/tools/lkml_converter.py
looker_loader/tools/llm.py
looker_loader/tools/recipe_mixer.py
looker_loader/tools/string_manipulation.py
looker_loader-0.1.50.dist-info/METADATA
looker_loader-0.1.50.dist-info/WHEEL
looker_loader-0.1.50.dist-info/entry_points.txt
looker_loader-0.1.50.dist-info/licenses/LICENSE
looker_loader-0.1.50.dist-info/RECORD
