Metadata-Version: 2.4
Name: looker_loader
Version: 0.1.50
Summary: a tool for flexibly loading schemas from bigquery into looker
License-File: LICENSE
Requires-Python: >=3.10
Requires-Dist: aiohttp>=3.11.18
Requires-Dist: curio>=1.6
Requires-Dist: google-cloud-bigquery>=3.30.0
Requires-Dist: httpx>=0.28.1
Requires-Dist: jinja2>=3.1.6
Requires-Dist: lkml>=1.3.7
Requires-Dist: pydantic>=2.10.6
Requires-Dist: pytest>=8.3.5
Requires-Dist: pyyaml>=6.0.2
Requires-Dist: rich-argparse>=1.7.1
Requires-Dist: rich>=13.9.4
Requires-Dist: ruamel-yaml>=0.18.10
